statcord/__init__.py
statcord/client.py
statcord/cluster_client.py
betterstatcord.py-3.5.0.dist-info/LICENSE
betterstatcord.py-3.5.0.dist-info/WHEEL
betterstatcord.py-3.5.0.dist-info/METADATA
betterstatcord.py-3.5.0.dist-info/RECORD
