Metadata-Version: 2.1
Name: betterstatcord.py
Version: 3.5.0
Summary: A better Statcord API library for Python + Discord.py and its forks
Home-page: https://github.com/Iapetus-11/betterstatcord.py
License: MIT
Author: Milo Weinberg
Author-email: iapetus011@gmail.com
Requires-Python: >=3.7,<4.0
Classifier: License :: OSI Approved :: MIT License
Classifier: Programming Language :: Python :: 3
Classifier: Programming Language :: Python :: 3.10
Classifier: Programming Language :: Python :: 3.7
Classifier: Programming Language :: Python :: 3.8
Classifier: Programming Language :: Python :: 3.9
Requires-Dist: aiohttp (>=3.7.4,<4.0.0)
Requires-Dist: psutil (>=5.8.0,<6.0.0)
Project-URL: Repository, https://github.com/Iapetus-11/betterstatcord.py
